README.md
setup.py
pulumi_pnap/__init__.py
pulumi_pnap/provider.py
pulumi_pnap/server.py
pulumi_pnap/tables.py
pulumi_pnap/utilities.py
pulumi_pnap.egg-info/PKG-INFO
pulumi_pnap.egg-info/SOURCES.txt
pulumi_pnap.egg-info/dependency_links.txt
pulumi_pnap.egg-info/not-zip-safe
pulumi_pnap.egg-info/requires.txt
pulumi_pnap.egg-info/top_level.txt