Metadata-Version: 2.1
Name: pulumi-pnap
Version: 0.9.0
Summary: A PNAP package for creating and managing cloud resources.
Home-page: https://pulumi.io
License: Apache-2.0
Project-URL: Repository, https://github.com/phoenixnap/pulumi-pnap
Keywords: pulumi pnap
Platform: UNKNOWN
